{
    "set_number": "10696-1",
    "set_name": "Medium Creative Brick Box",
    "parts": [
        {
            "part_num": "11153",
            "part_name": "Slope Curved 4 x 1 No Studs [Stud Holder with Symmetric Ridges]",
            "quantity": 4
        },
        {
            "part_num": "11477",
            "part_name": "Slope Curved 2 x 1 No Studs [1/2 Bow]",
            "quantity": 2
        },
        {
            "part_num": "13971",
            "part_name": "Wheel 18 x 8 with Fake Bolts and Deep Spokes with Inner Ring",
            "quantity": 10
        },
        {
            "part_num": "15397",
            "part_name": "Plate 3 x 3 Cross",
            "quantity": 1
        },
        {
            "part_num": "15573",
            "part_name": "Plate Special 1 x 2 with 1 Stud with Groove and Inside Stud Holder (Jumper)",
            "quantity": 1
        },
        {
            "part_num": "2412b",
            "part_name": "Tile Special 1 x 2 Grille with Bottom Groove",
            "quantity": 6
        },
        {
            "part_num": "2431",
            "part_name": "Tile 1 x 4 with Groove",
            "quantity": 6
        },
        {
            "part_num": "2479",
            "part_name": "Propeller 4 Blade 5 Diameter with Rounded Ends, Open Hub",
            "quantity": 1
        },
        {
            "part_num": "2926",
            "part_name": "Plate Special 1 x 4 with Wheels Holder",
            "quantity": 2
        },
        {
            "part_num": "30000",
            "part_name": "Brick Special 2 x 2 with 2 Pins and Axle Hole",
            "quantity": 5
        },
        {
            "part_num": "3001",
            "part_name": "Brick 2 x 4",
            "quantity": 27
        },
        {
            "part_num": "3002",
            "part_name": "Brick 2 x 3",
            "quantity": 4
        },
        {
            "part_num": "3003",
            "part_name": "Brick 2 x 2",
            "quantity": 12
        },
        {
            "part_num": "3004",
            "part_name": "Brick 1 x 2",
            "quantity": 59
        },
        {
            "part_num": "30044",
            "part_name": "Window 1 x 2 x 2 2/3 with Rounded Top",
            "quantity": 1
        },
        {
            "part_num": "3005",
            "part_name": "Brick 1 x 1",
            "quantity": 8
        },
        {
            "part_num": "3007",
            "part_name": "Brick 2 x 8",
            "quantity": 3
        },
        {
            "part_num": "3009",
            "part_name": "Brick 1 x 6",
            "quantity": 4
        },
        {
            "part_num": "3010",
            "part_name": "Brick 1 x 4",
            "quantity": 24
        },
        {
            "part_num": "3020",
            "part_name": "Plate 2 x 4",
            "quantity": 7
        },
        {
            "part_num": "3021",
            "part_name": "Plate 2 x 3",
            "quantity": 3
        },
        {
            "part_num": "3022",
            "part_name": "Plate 2 x 2",
            "quantity": 2
        },
        {
            "part_num": "3023",
            "part_name": "Plate 1 x 2",
            "quantity": 9
        },
        {
            "part_num": "30236",
            "part_name": "Brick Special 1 x 2 with Handle",
            "quantity": 1
        },
        {
            "part_num": "3031",
            "part_name": "Plate 4 x 4",
            "quantity": 4
        },
        {
            "part_num": "3032",
            "part_name": "Plate 4 x 6",
            "quantity": 2
        },
        {
            "part_num": "3034",
            "part_name": "Plate 2 x 8",
            "quantity": 1
        },
        {
            "part_num": "3035",
            "part_name": "Plate 4 x 8",
            "quantity": 1
        },
        {
            "part_num": "3036",
            "part_name": "Plate 6 x 8",
            "quantity": 1
        },
        {
            "part_num": "3037",
            "part_name": "Slope 45\u00b0 2 x 4",
            "quantity": 1
        },
        {
            "part_num": "3039",
            "part_name": "Slope 45\u00b0 2 x 2",
            "quantity": 13
        },
        {
            "part_num": "3040b",
            "part_name": "Slope 45\u00b0 2 x 1 with Bottom Pin",
            "quantity": 38
        },
        {
            "part_num": "30414",
            "part_name": "Brick Special 1 x 4 with 4 Studs on One Side",
            "quantity": 2
        },
        {
            "part_num": "3062b",
            "part_name": "Brick Round 1 x 1 Open Stud",
            "quantity": 4
        },
        {
            "part_num": "3065",
            "part_name": "Brick 1 x 2 without Bottom Tube",
            "quantity": 6
        },
        {
            "part_num": "3069b",
            "part_name": "Tile 1 x 2 with Groove",
            "quantity": 4
        },
        {
            "part_num": "3184",
            "part_name": "Plate Special 1 x 4 with Towball",
            "quantity": 1
        },
        {
            "part_num": "3622",
            "part_name": "Brick 1 x 3",
            "quantity": 2
        },
        {
            "part_num": "3623",
            "part_name": "Plate 1 x 3",
            "quantity": 4
        },
        {
            "part_num": "3659",
            "part_name": "Brick Arch 1 x 4",
            "quantity": 2
        },
        {
            "part_num": "3660",
            "part_name": "Slope Inverted 45\u00b0 2 x 2 [Ovoid Bottom Pin, Bar-sized Stud Holes]",
            "quantity": 4
        },
        {
            "part_num": "3665",
            "part_name": "Slope Inverted 45\u00b0 2 x 1",
            "quantity": 10
        },
        {
            "part_num": "3666",
            "part_name": "Plate 1 x 6",
            "quantity": 4
        },
        {
            "part_num": "3679",
            "part_name": "Turntable 2 x 2 Plate - Top",
            "quantity": 1
        },
        {
            "part_num": "3680",
            "part_name": "Turntable 2 x 2 Plate, Base",
            "quantity": 1
        },
        {
            "part_num": "3710",
            "part_name": "Plate 1 x 4",
            "quantity": 13
        },
        {
            "part_num": "3747b",
            "part_name": "Slope Inverted 33\u00b0 3 x 2 [Connections between Studs]",
            "quantity": 3
        },
        {
            "part_num": "3795",
            "part_name": "Plate 2 x 6",
            "quantity": 2
        },
        {
            "part_num": "3941",
            "part_name": "Brick Round 2 x 2 with Axle Hole",
            "quantity": 11
        },
        {
            "part_num": "4032a",
            "part_name": "Plate Round 2 x 2 with Axle Hole Type 1 (+ Opening)",
            "quantity": 1
        },
        {
            "part_num": "4070",
            "part_name": "Brick Special 1 x 1 with Headlight",
            "quantity": 4
        },
        {
            "part_num": "4286",
            "part_name": "Slope 33\u00b0 3 x 1",
            "quantity": 2
        },
        {
            "part_num": "4460b",
            "part_name": "Slope 75\u00b0 2 x 1 x 3 with Hollow Stud",
            "quantity": 2
        },
        {
            "part_num": "44728",
            "part_name": "Bracket 1 x 2 - 2 x 2",
            "quantity": 2
        },
        {
            "part_num": "4600",
            "part_name": "Plate Special 2 x 2 with Wheel Holders",
            "quantity": 2
        },
        {
            "part_num": "4624",
            "part_name": "Wheel 8 x 6",
            "quantity": 5
        },
        {
            "part_num": "49668",
            "part_name": "Plate Special 1 x 1 with Tooth",
            "quantity": 2
        },
        {
            "part_num": "50950",
            "part_name": "Slope Curved 3 x 1 No Studs",
            "quantity": 4
        },
        {
            "part_num": "54200",
            "part_name": "Slope 30\u00b0 1 x 1 x 2/3 (Cheese Slope)",
            "quantity": 8
        },
        {
            "part_num": "59900",
            "part_name": "Cone 1 x 1 [Top Groove]",
            "quantity": 5
        },
        {
            "part_num": "60032",
            "part_name": "Window 1 x 2 x 2 Plane, Hollow Studs, Single Hole Top and Bottom for Glass",
            "quantity": 11
        },
        {
            "part_num": "6014b",
            "part_name": "Wheel 11 x 12 with Hole Notched for Wheels Holder Pin",
            "quantity": 4
        },
        {
            "part_num": "60478",
            "part_name": "Plate Special 1 x 2 with Handle on End [Closed Ends]",
            "quantity": 1
        },
        {
            "part_num": "60481",
            "part_name": "Slope 65\u00b0 2 x 1 x 2",
            "quantity": 4
        },
        {
            "part_num": "6091",
            "part_name": "Brick Curved 1 x 2 x 1 1/3 with Curved Top",
            "quantity": 12
        },
        {
            "part_num": "61252",
            "part_name": "Plate Special 1 x 1 with Clip Horizontal [Thick Open O Clip]",
            "quantity": 4
        },
        {
            "part_num": "61254",
            "part_name": "Tyre Offset Tread with Center Band 23 x 7",
            "quantity": 10
        },
        {
            "part_num": "6141",
            "part_name": "Plate Round 1 x 1 with Solid Stud",
            "quantity": 20
        },
        {
            "part_num": "6215",
            "part_name": "Brick Curved 2 x 3",
            "quantity": 2
        },
        {
            "part_num": "6232",
            "part_name": "Brick Special 2 x 2 with Pin and Axle Hole",
            "quantity": 1
        },
        {
            "part_num": "63868",
            "part_name": "Plate Special 1 x 2 with Clip Horizontal on End",
            "quantity": 5
        },
        {
            "part_num": "64799",
            "part_name": "Plate Special 4 x 4 with 2 x 2 Opening",
            "quantity": 1
        },
        {
            "part_num": "75937",
            "part_name": "Plate Special 2 x 2 with Bar Frame Octagonal, Reinforced, Completely Round Studs",
            "quantity": 1
        },
        {
            "part_num": "85984",
            "part_name": "Slope 30\u00b0 1 x 2 x 2/3",
            "quantity": 4
        },
        {
            "part_num": "87079",
            "part_name": "Tile 2 x 4 with Groove",
            "quantity": 2
        },
        {
            "part_num": "87087",
            "part_name": "Brick Special 1 x 1 with Stud on 1 Side",
            "quantity": 6
        },
        {
            "part_num": "87414",
            "part_name": "Tyre 15 x 6 Offset Tread Small with Band around Center",
            "quantity": 4
        },
        {
            "part_num": "87580",
            "part_name": "Plate Special 2 x 2 with Groove and Center Stud (Jumper)",
            "quantity": 2
        },
        {
            "part_num": "87697",
            "part_name": "Tyre 21 x 12 with Offset Tread Small Wide and Center Band",
            "quantity": 4
        },
        {
            "part_num": "88292",
            "part_name": "Brick Arch 1 x 3 x 2",
            "quantity": 1
        },
        {
            "part_num": "88930",
            "part_name": "Slope Brick Curved 2 x 4 x 2/3 No Studs, with Bottom Tubes",
            "quantity": 2
        },
        {
            "part_num": "92438",
            "part_name": "Plate 8 x 16",
            "quantity": 1
        },
        {
            "part_num": "92947",
            "part_name": "Brick Round 2 x 2 [Grill]",
            "quantity": 1
        },
        {
            "part_num": "93273",
            "part_name": "Slope Curved 4 x 1 Double with No Studs",
            "quantity": 2
        },
        {
            "part_num": "94161",
            "part_name": "Window 1 x 2 x 2 2/3 Shutter with Rounded Top",
            "quantity": 1
        },
        {
            "part_num": "96874",
            "part_name": "Brick and Axle Separator v2.0",
            "quantity": 1
        },
        {
            "part_num": "98100",
            "part_name": "Brick Round 2 x 2 Truncated Cone",
            "quantity": 1
        },
        {
            "part_num": "98138pr0008",
            "part_name": "Tile Round 1 x 1 with Offset Black Eye Print",
            "quantity": 3
        },
        {
            "part_num": "98138pr0026",
            "part_name": "Tile Round 1 x 1 with Black Eye Closed with Eyelashes Print",
            "quantity": 3
        },
        {
            "part_num": "98138pr0027",
            "part_name": "Tile Round 1 x 1 with Black Eye with Off-Side Pupil Partially Closed Print",
            "quantity": 3
        },
        {
            "part_num": "98263",
            "part_name": "Plate Special 1 x 4 with Coupling Link Double",
            "quantity": 2
        },
        {
            "part_num": "98560",
            "part_name": "Slope 75\u00b0 2 x 2 x 3 [Solid Studs]",
            "quantity": 2
        }
    ]
}